dmenu-0.2.1.dist-info/RECORD
dmenu-0.2.1.dist-info/WHEEL
dmenu-0.2.1.dist-info/METADATA
dmenu-0.2.1.dist-info/DESCRIPTION.rst
dmenu-0.2.1.dist-info/top_level.txt
dmenu-0.2.1.dist-info/metadata.json
dmenu/__init__.py
dmenu/dmenu.py
